smartyaml/__init__.py
smartyaml/config.py
smartyaml/constants.py
smartyaml/error_context.py
smartyaml/exceptions.py
smartyaml/loader.py
smartyaml/merge.py
smartyaml/performance_optimizations.py
smartyaml/py.typed
smartyaml/registry.py
smartyaml/testing_utils.py
smartyaml/type_annotations.py
smartyaml/constructors/__init__.py
smartyaml/constructors/base.py
smartyaml/constructors/conditional.py
smartyaml/constructors/encoding.py
smartyaml/constructors/environment.py
smartyaml/constructors/expansion.py
smartyaml/constructors/extend.py
smartyaml/constructors/import_yaml_merge.py
smartyaml/constructors/imports.py
smartyaml/constructors/templates.py
smartyaml/constructors/yaml_file_loader.py
smartyaml/loading/__init__.py
smartyaml/loading/content_reader.py
smartyaml/loading/inline_template_processor.py
smartyaml/loading/pipeline.py
smartyaml/loading/template_preprocessor.py
smartyaml/loading/variable_merger.py
smartyaml/parsing/__init__.py
smartyaml/parsing/parameter_processors.py
smartyaml/parsing/tag_parser.py
smartyaml/processing/__init__.py
smartyaml/processing/parameter_extractor.py
smartyaml/processing/parameter_validator.py
smartyaml/processing/type_converter.py
smartyaml/utils/__init__.py
smartyaml/utils/file_utils.py
smartyaml/utils/loader_utils.py
smartyaml/utils/path_utils.py
smartyaml/utils/validation_utils.py
smartyaml/utils/variable_substitution.py
smartyaml/utils/yaml_parsing.py
pysmartyaml-0.1.0.dist-info/METADATA
pysmartyaml-0.1.0.dist-info/WHEEL
pysmartyaml-0.1.0.dist-info/top_level.txt
pysmartyaml-0.1.0.dist-info/RECORD
