Metadata-Version: 2.4
Name: pysmartyaml
Version: 0.1.0
Summary: Extended YAML format with custom directives for imports, environment variables, and more
Author-email: Albert Puigsech <albert@puigsech.com>
Maintainer-email: Albert Puigsech <albert@puigsech.com>
License-Expression: MIT
Project-URL: Homepage, https://github.com/apuigsech/smartyaml
Project-URL: Bug Reports, https://github.com/apuigsech/smartyaml/issues
Project-URL: Source, https://github.com/apuigsech/smartyaml
Project-URL: Documentation, https://github.com/apuigsech/smartyaml#readme
Project-URL: Changelog, https://github.com/apuigsech/smartyaml/blob/main/CHANGELOG.md
Keywords: yaml,configuration,import,environment,template
Classifier: Development Status :: 3 - Alpha
Classifier: Intended Audience :: Developers
Classifier: Programming Language :: Python :: 3
Classifier: Programming Language :: Python :: 3.9
Classifier: Programming Language :: Python :: 3.10
Classifier: Programming Language :: Python :: 3.11
Classifier: Programming Language :: Python :: 3.12
Classifier: Programming Language :: Python :: 3.13
Classifier: Topic :: Software Development :: Libraries :: Python Modules
Classifier: Topic :: Text Processing :: Markup
Requires-Python: >=3.9
Requires-Dist: PyYAML>=5.1
Provides-Extra: dev
Requires-Dist: pytest>=6.0; extra == "dev"
Requires-Dist: pytest-cov>=2.10; extra == "dev"
Requires-Dist: mypy>=1.0; extra == "dev"
Requires-Dist: black>=22.0; extra == "dev"
Requires-Dist: isort>=5.0; extra == "dev"
Requires-Dist: flake8>=4.0; extra == "dev"
Provides-Extra: test
Requires-Dist: pytest>=6.0; extra == "test"
Requires-Dist: pytest-cov>=2.10; extra == "test"
Requires-Dist: pytest-xdist>=2.0; extra == "test"
Provides-Extra: docs
Requires-Dist: sphinx>=4.0; extra == "docs"
Requires-Dist: sphinx-rtd-theme>=1.0; extra == "docs"
